ewl/__init__.py
ewl/games.py
ewl/ibmq.py
ewl/mixed.py
ewl/parametrizations.py
ewl/plotting.py
ewl/utils.py
ewl-0.10.0.dist-info/LICENSE
ewl-0.10.0.dist-info/METADATA
ewl-0.10.0.dist-info/WHEEL
ewl-0.10.0.dist-info/top_level.txt
ewl-0.10.0.dist-info/RECORD
