Metadata-Version: 2.1
Name: ewl
Version: 0.10.0
Summary: A simple Python library to simulate and execute EWL quantum circuits on IBM Q.
Home-page: https://github.com/tomekzaw/ewl
Author: Piotr Kotara, Tomasz Zawadzki
Author-email: piotrekkotara@gmail.com, tomekzawadzki98@gmail.com
License: UNKNOWN
Project-URL: Bug Tracker, https://github.com/tomekzaw/ewl/issues
Platform: UNKNOWN
Classifier: Programming Language :: Python :: 3
Classifier: License :: OSI Approved :: MIT License
Classifier: Operating System :: OS Independent
Requires-Python: >=3.6
License-File: LICENSE
